wagtail_cblocks/__init__.py
wagtail_cblocks/factories.py
wagtail_cblocks/blocks/__init__.py
wagtail_cblocks/blocks/migrations/__init__.py
wagtail_cblocks/blocks/migrations/operations.py
wagtail_cblocks/locale/fr/LC_MESSAGES/django.mo
wagtail_cblocks/locale/fr/LC_MESSAGES/django.po
wagtail_cblocks/static/wagtail_cblocks/admin/css/link-target-block.css
wagtail_cblocks/static/wagtail_cblocks/admin/js/link-target-block.js
wagtail_cblocks/templates/wagtail_cblocks/button_block.html
wagtail_cblocks/templates/wagtail_cblocks/columns_block.html
wagtail_cblocks/templates/wagtail_cblocks/heading_block.html
wagtail_cblocks/templates/wagtail_cblocks/image_block.html
wagtail_cblocks/templates/wagtail_cblocks/paragraph_block.html
wagtail_cblocks/templates/wagtail_cblocks/sized_image_block.html
wagtail_cblocks/templates/wagtail_cblocks/admin/forms/link_target_block.html
wagtail_cblocks-0.6.0.dist-info/METADATA
wagtail_cblocks-0.6.0.dist-info/WHEEL
wagtail_cblocks-0.6.0.dist-info/licenses/LICENSE
wagtail_cblocks-0.6.0.dist-info/RECORD
