Metadata-Version: 2.4
Name: wagtail_cblocks
Version: 0.6.0
Summary: Collection of StreamField blocks for Wagtail
Project-URL: Repository, https://framagit.org/cliss21/wagtail-cblocks
Project-URL: Issues, https://framagit.org/cliss21/wagtail-cblocks/-/issues
Author-email: Cliss XXI <contact@cliss21.com>
License-Expression: AGPL-3.0-or-later
License-File: LICENSE
Keywords: blocks,streamfield,wagtail
Classifier: Development Status :: 3 - Alpha
Classifier: Environment :: Web Environment
Classifier: Framework :: Django
Classifier: Framework :: Wagtail
Classifier: Intended Audience :: Developers
Classifier: License :: OSI Approved :: GNU Affero General Public License v3
Classifier: Programming Language :: Python :: 3
Classifier: Programming Language :: Python :: 3.10
Classifier: Programming Language :: Python :: 3.11
Classifier: Programming Language :: Python :: 3.12
Classifier: Programming Language :: Python :: 3.13
Requires-Python: >=3.10
Requires-Dist: django>=4.2
Requires-Dist: wagtail>=6.3
Provides-Extra: factories
Requires-Dist: wagtail-factories>=4.0.0; extra == 'factories'
